[
  {
    "position": "Docente / Colaborador Académico",
    "company": "TECSUP – Instituto Superior Tecnológico",
    "duration": "2015 – Actualidad",
    "location": "Arequipa, Perú",
    "description": "Diseño y ejecución de cursos de Redes, Sistemas Operativos, Ciberseguridad y Cloud.\nImplementación de laboratorios virtuales y plataformas de educación híbrida.",
    "responsibilities": [
      "Coordinación académica y liderazgo de programas de actualización técnica",
      "Diseño de planes de estudio para carreras técnicas",
      "Implementación de tecnologías educativas innovadoras"
    ],
    "technologies": ["Cisco", "VMware", "Linux", "Windows Server", "Cloud"]
  },
  {
    "position": "Ingeniero Preventa",
    "company": "iTERA S.A.C.",
    "duration": "Julio 2017 - Diciembre 2019 (2 años 6 meses)",
    "location": "Lima, Perú",
    "description": "Jornada completa",
    "responsibilities": [
      "Soporte preventa de soluciones: Fortigate, ESET corporativo, Acronis, Synology, VMware, Safetica, Ubiquiti y Veeam",
      "Implementación de firewalls Fortigate (modelos: 50E, 60E, 100E, 200E)",
      "Instalación y administración de servidores virtualizados con VMware vSphere 5.5 a 6.7",
      "Administración de servidores Windows: DNS, DHCP, Active Directory, File Server, Print Server",
      "Soporte técnico a entornos Linux",
      "Configuración de soluciones de seguridad (Safetica, ESET)"
    ],
    "technologies": ["Fortigate", "VMware", "Windows Server", "Linux", "ESET"]
  },
  {
    "position": "Soporte TI",
    "company": "iTERA S.A.C.",
    "duration": "Octubre 2016 - Marzo 2017 (6 meses)",
    "location": "San Miguel, Lima",
    "responsibilities": [
      "Soporte técnico integral: remoto, presencial y telefónico",
      "Capacitación a usuarios sobre soluciones tecnológicas",
      "Implementación de backups con Acronis y NAS Synology",
      "Mantenimiento de redes y estaciones de trabajo",
      "Instalación de Windows Desktop y Server (2008 a 2016)"
    ],
    "technologies": ["Windows Server", "Acronis", "Synology", "Soporte TI"]
  },
  {
    "position": "Soporte TI",
    "company": "EngiPerú",
    "duration": "Octubre 2015 - Julio 2016 (10 meses)",
    "location": "Lima, Perú",
    "responsibilities": [
      "Implementación y soporte remoto de soluciones de seguridad TI",
      "Apoyo al área comercial en preventa de productos de ciberseguridad",
      "Configuración básica de infraestructura en empresas clientes"
    ],
    "technologies": ["Seguridad Informática", "Soporte Remoto"]
  },
  {
    "position": "Practicante – Control de Procesos",
    "company": "Southern Peru Copper Corporation (SPCC)",
    "duration": "Febrero 2015 - Julio 2015 (6 meses)",
    "location": "Toquepala",
    "responsibilities": [
      "Apoyo en monitoreo y documentación de variables de control de procesos industriales",
      "Colaboración en actividades de mejora continua dentro de planta"
    ]
  }
]
